gusto/__init__.py
gusto/agents.py
gusto/tools.py
gusto/utils.py
gusto/types/__init__.py
gusto/types/chat_messages.py
gusto/types/chat_request.py
gusto/types/chat_response.py
gusto-0.2.0.dist-info/METADATA
gusto-0.2.0.dist-info/WHEEL
gusto-0.2.0.dist-info/top_level.txt
gusto-0.2.0.dist-info/RECORD
